{
  "dataset": "sst2",
  "standard_lora": null,
  "sequential_paths": {
    "28-16-4": {
      "epoch_allocation": [
        28,
        16,
        4
      ],
      "component_history": [
        {
          "component_index": 1,
          "epochs": 28,
          "accuracy_after": 0.875,
          "validation_loss_after": 0.29694750905036926
        },
        {
          "component_index": 2,
          "epochs": 16,
          "accuracy_after": 0.8738532110091743,
          "validation_loss_after": 0.2915688753128052
        },
        {
          "component_index": 3,
          "epochs": 4,
          "accuracy_after": 0.8761467889908257,
          "validation_loss_after": 0.2914336323738098
        }
      ],
      "final_accuracy": 0.8761467889908257,
      "total_epochs": 48,
      "trainable_params": 18432,
      "total_params": 67065602,
      "training_time_seconds": 2121.3309030532837
    }
  },
  "ablation_config": {
    "type": "sequential",
    "rank": 3,
    "total_epochs": 48,
    "alpha": 0.8,
    "schedule": [
      28,
      16,
      4
    ],
    "schedule_str": "28-16-4"
  },
  "config": {
    "model_name": "distilbert-base-uncased",
    "batch_size": 32,
    "learning_rate": 2e-05,
    "weight_decay": 0.01,
    "max_length": 128,
    "precision": "bf16"
  },
  "flops": {
    "architecture": "distilbert_qv",
    "layers": [
      [
        768,
        768
      ],
      [
        768,
        768
      ],
      [
        768,
        768
      ],
      [
        768,
        768
      ],
      [
        768,
        768
      ],
      [
        768,
        768
      ],
      [
        768,
        768
      ],
      [
        768,
        768
      ],
      [
        768,
        768
      ],
      [
        768,
        768
      ],
      [
        768,
        768
      ],
      [
        768,
        768
      ]
    ],
    "samples_per_epoch": 8620672,
    "num_train_examples": 67349,
    "max_length": 128
  }
}